dev/__init__.py
dev/__main__.py
dev/analytics.py
dev/args.py
dev/args_formatter.py
dev/commands.py
dev/copypaste.py
dev/diffs.py
dev/dump.py
dev/editor.py
dev/exceptions.py
dev/format_settings.py
dev/gui.py
dev/help.py
dev/help_pats.py
dev/history.py
dev/io.py
dev/linter.py
dev/llm.py
dev/main.py
dev/mdstream.py
dev/models.py
dev/prompts.py
dev/repo.py
dev/repomap.py
dev/report.py
dev/run_cmd.py
dev/scrape.py
dev/sendchat.py
dev/special.py
dev/urls.py
dev/utils.py
dev/versioncheck.py
dev/voice.py
dev/watch.py
dev/watch_prompts.py
dev/coders/__init__.py
dev/coders/architect_coder.py
dev/coders/architect_prompts.py
dev/coders/ask_coder.py
dev/coders/ask_prompts.py
dev/coders/base_coder.py
dev/coders/base_prompts.py
dev/coders/chat_chunks.py
dev/coders/editblock_coder.py
dev/coders/editblock_fenced_coder.py
dev/coders/editblock_fenced_prompts.py
dev/coders/editblock_func_coder.py
dev/coders/editblock_func_prompts.py
dev/coders/editblock_prompts.py
dev/coders/editor_editblock_coder.py
dev/coders/editor_editblock_prompts.py
dev/coders/editor_whole_coder.py
dev/coders/editor_whole_prompts.py
dev/coders/help_coder.py
dev/coders/help_prompts.py
dev/coders/search_replace.py
dev/coders/single_wholefile_func_coder.py
dev/coders/single_wholefile_func_prompts.py
dev/coders/udiff_coder.py
dev/coders/udiff_prompts.py
dev/coders/wholefile_coder.py
dev/coders/wholefile_func_coder.py
dev/coders/wholefile_func_prompts.py
dev/coders/wholefile_prompts.py
dev/queries/tree-sitter-language-pack/javascript-tags.scm
dev/queries/tree-sitter-languages/README.md
dev/queries/tree-sitter-languages/c-tags.scm
dev/queries/tree-sitter-languages/c_sharp-tags.scm
dev/queries/tree-sitter-languages/cpp-tags.scm
dev/queries/tree-sitter-languages/dart-tags.scm
dev/queries/tree-sitter-languages/elisp-tags.scm
dev/queries/tree-sitter-languages/elixir-tags.scm
dev/queries/tree-sitter-languages/elm-tags.scm
dev/queries/tree-sitter-languages/go-tags.scm
dev/queries/tree-sitter-languages/hcl-tags.scm
dev_install-0.0.2.dist-info/LICENSE.txt
dev_install-0.0.2.dist-info/METADATA
dev_install-0.0.2.dist-info/WHEEL
dev_install-0.0.2.dist-info/entry_points.txt
dev_install-0.0.2.dist-info/top_level.txt
dev_install-0.0.2.dist-info/RECORD
